README.md
setup.py
pstraw/__init__.py
pstraw/bean_factory.py
pstraw/db_guide.py
pstraw/definition.py
pstraw/frame_guide.py
pstraw/loadenv.py
pstraw/logger_factory.py
pstraw/orm_factory.py
pstraw/resource_factory.py
pstraw/screws.py
pstraw/template_factory.py
pstraw/tool.py
pstraw.egg-info/PKG-INFO
pstraw.egg-info/SOURCES.txt
pstraw.egg-info/dependency_links.txt
pstraw.egg-info/requires.txt
pstraw.egg-info/top_level.txt
pstraw/loader/__init__.py
pstraw/loader/extends.py
pstraw/loader/sqlalchemy.py
ptest/__init__.py